state_signals.py
state_signals-1.0.1.dist-info/LICENSE
state_signals-1.0.1.dist-info/WHEEL
state_signals-1.0.1.dist-info/METADATA
state_signals-1.0.1.dist-info/RECORD
