Metadata-Version: 2.1
Name: state-signals
Version: 1.0.1
Summary: Package for easy management of state/event signal publishing, subscribing, and responding
Home-page: https://github.com/distributed-system-analysis/state-signals
License: GPL-3.0-only
Keywords: state,event,signal,publish,subscribe
Author: Mustafa Eyceoz
Author-email: meyceoz@redhat.com
Requires-Python: >=3.6,<4.0
Classifier: License :: OSI Approved :: GNU General Public License v3 (GPLv3)
Classifier: Programming Language :: Python :: 3
Classifier: Programming Language :: Python :: 3.6
Classifier: Programming Language :: Python :: 3.7
Classifier: Programming Language :: Python :: 3.8
Classifier: Programming Language :: Python :: 3.9
Requires-Dist: dataclasses (>=0.6,<0.7); python_version >= "3.6" and python_version < "3.7"
Requires-Dist: redis (>=3.5,<4.0)
Project-URL: Repository, https://github.com/distributed-system-analysis/state-signals
